greednought/__init__.py
greednought/greednought.py
greednought-0.1.3.dist-info/licenses/LICENSE
greednought-0.1.3.dist-info/WHEEL
greednought-0.1.3.dist-info/entry_points.txt
greednought-0.1.3.dist-info/METADATA
greednought-0.1.3.dist-info/RECORD
