Metadata-Version: 2.4
Name: greednought
Version: 0.1.3
Summary: A text adventure game created for Week 5 of Hack Club's Siege
License-Expression: GPL-3.0-only
License-File: LICENSE
Requires-Python: >=3.12
